LICENSE
MANIFEST.in
README.rst
setup.py
django_toffee.egg-info/PKG-INFO
django_toffee.egg-info/SOURCES.txt
django_toffee.egg-info/dependency_links.txt
django_toffee.egg-info/requires.txt
django_toffee.egg-info/top_level.txt
toffee/__init__.py
toffee/helpers.py
toffee/tests.py
toffee/ui.py
toffee/utils.py
toffee/static/style.css
toffee/static/css/bootstrap-theme.min.css
toffee/static/css/bootstrap.min.css
toffee/static/css/jquery.dataTables.css
toffee/static/fonts/glyphicons-halflings-regular.eot
toffee/static/fonts/glyphicons-halflings-regular.svg
toffee/static/fonts/glyphicons-halflings-regular.ttf
toffee/static/fonts/glyphicons-halflings-regular.woff
toffee/static/js/bootstrap.min.js
toffee/static/js/bootstrap3-confirmation.js
toffee/static/js/datatableview.js
toffee/static/js/jquery-1.10.1.min.js
toffee/static/js/jquery-1.10.1.min.map
toffee/static/js/jquery-migrate-1.2.1.min.js
toffee/static/js/jquery.dataTables.bootstrap.js
toffee/static/js/jquery.dataTables.columnFilter.js
toffee/static/js/jquery.dataTables.min.js
toffee/static/js/script.js
toffee/templates/app_form.html
toffee/templates/app_tabgroup.html
toffee/templates/app_table.html
toffee/templates/app_template.html
toffee/templatetags/__init__.py
toffee/templatetags/__init__.pyc
toffee/templatetags/addcss.py
toffee/templatetags/addcss.pyc