Metadata-Version: 1.1
Name: django-toffee
Version: 0.26
Summary: A simple Django app to layout your applications.
Home-page: http://www.bingorabbit.com/
Author: Ibrahim Abdel Fattah Mohamed
Author-email: bingorabbit@gmail.com
License: BSD License
Platform: UNKNOWN
Classifier: Environment :: Web Environment
Classifier: Framework :: Django
Classifier: Intended Audience :: Developers
Classifier: License :: OSI Approved :: BSD License
Classifier: Operating System :: OS Independent
Classifier: Programming Language :: Python
Classifier: Programming Language :: Python :: 2
Classifier: Programming Language :: Python :: 2.7
Classifier: Topic :: Internet :: WWW/HTTP
Classifier: Topic :: Internet :: WWW/HTTP :: Dynamic Content
